schools/__init__.py
schools/admin.py
schools/apps.py
schools/forms.py
schools/helpers.py
schools/models.py
schools/tests.py
schools/tokens.py
schools/urls.py
schools/views.py
schools/migrations/0001_initial.py
schools/migrations/__init__.py
schools/templates/schools/account-expired.html
schools/templates/schools/change-department.html
schools/templates/schools/create-department.html
schools/templates/schools/edit-user-departments.html
schools/templates/schools/faculty_confirm_delete.html
schools/templates/schools/invite-users.html
schools/templates/schools/manage-departments.html
schools/templates/schools/user-join-department.html
schools/templates/schools/view-department.html
django_schools_hashtag_learning-0.1.2.dist-info/LICENCE
django_schools_hashtag_learning-0.1.2.dist-info/METADATA
django_schools_hashtag_learning-0.1.2.dist-info/WHEEL
django_schools_hashtag_learning-0.1.2.dist-info/top_level.txt
django_schools_hashtag_learning-0.1.2.dist-info/RECORD
