Metadata-Version: 2.1
Name: django-schools-hashtag-learning
Version: 0.1.2
Summary: Used with Hashtag Learning resources.
Home-page: https://github.com/mark-cunningham
Author: Mark Cunningham
Author-email: mark@hashtag-learning.co.uk
License: BSD License
Platform: UNKNOWN
Classifier: Environment :: Web Environment
Classifier: Framework :: Django
Classifier: Framework :: Django :: 2.2
Classifier: Intended Audience :: Developers
Classifier: License :: OSI Approved :: BSD License
Classifier: Operating System :: OS Independent
Classifier: Programming Language :: Python
Classifier: Programming Language :: Python :: 3.5
Classifier: Programming Language :: Python :: 3.6
Classifier: Topic :: Internet :: WWW/HTTP
Classifier: Topic :: Internet :: WWW/HTTP :: Dynamic Content
